Workbook

Sheet Resumen
A1: Plantilla de carga - Analiza en Casa
A2: Complete las hojas de catalogo antes de importar al sistema. Mantenga los encabezados y revise la columna validacion_minima.
A4: Catalogo | B4: Registros con ID | C4: Filas incompletas | D4: Primer paso sugerido
A5: Servicios | B5: =COUNTIFS(Servicios!$A$6:$A$205,"<>") -> 0 | C5: =COUNTIFS(Servicios!$N$6:$N$205,"Falta dato obligatorio") -> 0 | D5: Cargar nombre, categoria, unidad de cobro y estatus.
A6: Proveedores | B6: =COUNTIFS(Proveedores!$A$6:$A$205,"<>") -> 0 | C6: =COUNTIFS(Proveedores!$R$6:$R$205,"Falta dato obligatorio") -> 0 | D6: Registrar datos de contacto y contrato vigente.
A7: Seguros | B7: =COUNTIFS(Seguros!$A$6:$A$205,"<>") -> 0 | C7: =COUNTIFS(Seguros!$P$6:$P$205,"Falta dato obligatorio") -> 0 | D7: Registrar aseguradora, plan, autorizaciones y vigencia.
A8: Productos | B8: =COUNTIFS(Productos!$A$6:$A$205,"<>") -> 0 | C8: =COUNTIFS(Productos!$O$6:$O$205,"Falta dato obligatorio") -> 0 | D8: Registrar unidad, costo, precio e inventario minimo.
A9: Tarifas_Coberturas | B9: =COUNTIFS(Tarifas_Coberturas!$A$6:$A$205,"<>") -> 0 | C9: =COUNTIFS(Tarifas_Coberturas!$O$6:$O$205,"Falta dato obligatorio") -> 0 | D9: Relacionar servicios con seguros, proveedores y vigencias.
A10: Compras_Proveedor | B10: =COUNTIFS(Compras_Proveedor!$A$6:$A$205,"<>") -> 0 | C10: =COUNTIFS(Compras_Proveedor!$L$6:$L$205,"Falta dato obligatorio") -> 0 | D10: Relacionar productos con proveedores, costos y tiempos de entrega.
A11: Personal | B11: =COUNTIFS(Personal!$A$6:$A$205,"<>") -> 0 | C11: =COUNTIFS(Personal!$L$6:$L$205,"Falta dato obligatorio") -> 0 | D11: Registrar personal disponible y zona de cobertura.
A13: Orden recomendado de carga | D13: Reglas basicas
A14: 1 | B14: Proveedores, Seguros y Personal | D14: Use IDs unicos. Ej.: SERV-001, PROV-001, SEG-001.
A15: 2 | B15: Servicios y Productos | D15: No cambie hojas ni encabezados si el archivo se importara.
A16: 3 | B16: Tarifas_Coberturas | D16: Los desplegables vienen de Listas y pueden ampliarse.
A17: 4 | B17: Compras_Proveedor | D17: Escriba fechas como fechas reales.
A18: 5 | B18: Revisar filas incompletas en Resumen | D18: Capture montos como numeros, sin simbolos en la celda.
A19: 6 | B19: Importar al sistema o entregar al administrador | D19: validacion_minima avisa si faltan campos requeridos.
A21: Creado el | B21: 46281

Sheet Listas
A1: Listas para validacion
A2: Edite estas listas si el sistema necesita nuevos valores permitidos.
A4: Estatus | C4: SiNo | E4: TipoServicio | G4: UnidadCobro | I4: TipoProveedor | K4: TipoSeguro | M4: TipoProducto | O4: Moneda | Q4: CoberturaTipo | S4: Funcion | U4: Disponibilidad | W4: UnidadMedida
A5: Activo | C5: Si | E5: Enfermeria | G5: Visita | I5: Clinica | K5: Seguro privado | M5: Medicamento | O5: USD | Q5: No cubierto | S5: Enfermera general | U5: Tiempo completo | W5: Unidad
A6: Inactivo | C6: No | E6: Cuidado domiciliario | G6: Hora | I6: Hospital | K6: Seguro empresarial | M6: Insumo medico | O6: MXN | Q6: Porcentaje | S6: Auxiliar de enfermeria | U6: Medio tiempo | W6: Caja
A7: En revision | E7: Consulta | G7: Dia | I7: Laboratorio | K7: Convenio | M7: Equipo | O7: GTQ | Q7: Monto fijo | S7: Jefa de enfermeria | U7: Por turnos | W7: Frasco
E8: Procedimiento | G8: Semana | I8: Farmacia | K8: Particular | M8: Material de curacion | O8: HNL | Q8: Copago | S8: Cuidadora | U8: Bajo llamada | W8: Bolsa
E9: Laboratorio | G9: Mes | I9: Equipo medico | K9: Otro | M9: Higiene | O9: NIO | Q9: Incluido | S9: Otra funcion | U9: No disponible | W9: Par
E10: Terapia | G10: Sesion | I10: Transporte | M10: Otro | O10: CRC | W10: Kit
E11: Hospitalizacion | G11: Unidad | I11: Enfermeria externa | O11: DOP | W11: Litro
E12: Traslado | G12: Caja | I12: Aseguradora | W12: Mililitro
E13: Medicamento | I13: Otro | W13: Gramo
E14: Otro

Sheet Servicios
A1: Servicios
A2: Catalogo de servicios que el sistema puede cotizar, agendar o reportar.
A3: Campos requeridos: servicio_id, nombre_servicio, categoria, unidad_cobro, estatus
A4: Requerido | B4: Requerido | C4: Requerido | D4: Opcional | E4: Requerido | F4: Opcional | G4: Opcional | H4: Opcional | I4: Opcional | J4: Opcional | K4: Opcional | L4: Requerido | M4: Opcional | N4: Calculado
A5: servicio_id | B5: nombre_servicio | C5: categoria | D5: descripcion | E5: unidad_cobro | F5: duracion_minutos | G5: precio_base | H5: moneda | I5: requiere_autorizacion | J5: requiere_orden_medica | K5: aplica_a | L5: estatus | M5: notas | N5: validacion_minima
N6: =IF(COUNTA($A6:$M6)=0,"",IF(OR($A6="",$B6="",$C6="",$E6="",$L6=""),"Falta dato obligatorio","Listo"))
N7: =IF(COUNTA($A7:$M7)=0,"",IF(OR($A7="",$B7="",$C7="",$E7="",$L7=""),"Falta dato obligatorio","Listo"))
N8: =IF(COUNTA($A8:$M8)=0,"",IF(OR($A8="",$B8="",$C8="",$E8="",$L8=""),"Falta dato obligatorio","Listo"))
N9: =IF(COUNTA($A9:$M9)=0,"",IF(OR($A9="",$B9="",$C9="",$E9="",$L9=""),"Falta dato obligatorio","Listo"))
N10: =IF(COUNTA($A10:$M10)=0,"",IF(OR($A10="",$B10="",$C10="",$E10="",$L10=""),"Falta dato obligatorio","Listo"))
N11: =IF(COUNTA($A11:$M11)=0,"",IF(OR($A11="",$B11="",$C11="",$E11="",$L11=""),"Falta dato obligatorio","Listo"))
N12: =IF(COUNTA($A12:$M12)=0,"",IF(OR($A12="",$B12="",$C12="",$E12="",$L12=""),"Falta dato obligatorio","Listo"))
N13: =IF(COUNTA($A13:$M13)=0,"",IF(OR($A13="",$B13="",$C13="",$E13="",$L13=""),"Falta dato obligatorio","Listo"))
N14: =IF(COUNTA($A14:$M14)=0,"",IF(OR($A14="",$B14="",$C14="",$E14="",$L14=""),"Falta dato obligatorio","Listo"))
N15: =IF(COUNTA($A15:$M15)=0,"",IF(OR($A15="",$B15="",$C15="",$E15="",$L15=""),"Falta dato obligatorio","Listo"))
N16: =IF(COUNTA($A16:$M16)=0,"",IF(OR($A16="",$B16="",$C16="",$E16="",$L16=""),"Falta dato obligatorio","Listo"))
N17: =IF(COUNTA($A17:$M17)=0,"",IF(OR($A17="",$B17="",$C17="",$E17="",$L17=""),"Falta dato obligatorio","Listo"))
... N205: =IF(COUNTA($A205:$M205)=0,"",IF(OR($A205="",$B205="",$C205="",$E205="",$L205=""),"Falta dato obligatorio","Listo"))

Sheet Proveedores
A1: Proveedores
A2: Registro maestro de proveedores clinicos, operativos y comerciales.
A3: Campos requeridos: proveedor_id, nombre_proveedor, tipo_proveedor, estatus
A4: Requerido | B4: Requerido | C4: Requerido | D4: Requerido | E4: Opcional | F4: Opcional | G4: Opcional | H4: Opcional | I4: Opcional | J4: Opcional | K4: Opcional | L4: Opcional | M4: Opcional | N4: Opcional | O4: Opcional | P4: Opcional | Q4: Opcional | R4: Calculado
A5: proveedor_id | B5: nombre_proveedor | C5: tipo_proveedor | D5: estatus | E5: contacto_principal | F5: telefono | G5: email | H5: direccion | I5: ciudad | J5: pais | K5: ruc_nit | L5: especialidad | M5: horario_atencion | N5: contrato_vigente | O5: vigencia_desde | P5: vigencia_hasta | Q5: notas | R5: validacion_minima
R6: =IF(COUNTA($A6:$Q6)=0,"",IF(OR($A6="",$B6="",$C6="",$D6=""),"Falta dato obligatorio","Listo"))
R7: =IF(COUNTA($A7:$Q7)=0,"",IF(OR($A7="",$B7="",$C7="",$D7=""),"Falta dato obligatorio","Listo"))
R8: =IF(COUNTA($A8:$Q8)=0,"",IF(OR($A8="",$B8="",$C8="",$D8=""),"Falta dato obligatorio","Listo"))
R9: =IF(COUNTA($A9:$Q9)=0,"",IF(OR($A9="",$B9="",$C9="",$D9=""),"Falta dato obligatorio","Listo"))
R10: =IF(COUNTA($A10:$Q10)=0,"",IF(OR($A10="",$B10="",$C10="",$D10=""),"Falta dato obligatorio","Listo"))
R11: =IF(COUNTA($A11:$Q11)=0,"",IF(OR($A11="",$B11="",$C11="",$D11=""),"Falta dato obligatorio","Listo"))
R12: =IF(COUNTA($A12:$Q12)=0,"",IF(OR($A12="",$B12="",$C12="",$D12=""),"Falta dato obligatorio","Listo"))
R13: =IF(COUNTA($A13:$Q13)=0,"",IF(OR($A13="",$B13="",$C13="",$D13=""),"Falta dato obligatorio","Listo"))
R14: =IF(COUNTA($A14:$Q14)=0,"",IF(OR($A14="",$B14="",$C14="",$D14=""),"Falta dato obligatorio","Listo"))
R15: =IF(COUNTA($A15:$Q15)=0,"",IF(OR($A15="",$B15="",$C15="",$D15=""),"Falta dato obligatorio","Listo"))
R16: =IF(COUNTA($A16:$Q16)=0,"",IF(OR($A16="",$B16="",$C16="",$D16=""),"Falta dato obligatorio","Listo"))
R17: =IF(COUNTA($A17:$Q17)=0,"",IF(OR($A17="",$B17="",$C17="",$D17=""),"Falta dato obligatorio","Listo"))
... R205: =IF(COUNTA($A205:$Q205)=0,"",IF(OR($A205="",$B205="",$C205="",$D205=""),"Falta dato obligatorio","Listo"))

Sheet Seguros
A1: Seguros
A2: Aseguradoras, convenios y planes que pueden cubrir servicios o productos.
A3: Campos requeridos: seguro_id, aseguradora, plan_poliza, estatus
A4: Requerido | B4: Requerido | C4: Requerido | D4: Opcional | E4: Requerido | F4: Opcional | G4: Opcional | H4: Opcional | I4: Opcional | J4: Opcional | K4: Opcional | L4: Opcional | M4: Opcional | N4: Opcional | O4: Opcional | P4: Calculado
A5: seguro_id | B5: aseguradora | C5: plan_poliza | D5: tipo_plan | E5: estatus | F5: contacto_autorizaciones | G5: telefono | H5: email | I5: requiere_autorizacion | J5: copago_default | K5: deducible_default | L5: moneda | M5: vigencia_desde | N5: vigencia_hasta | O5: notas | P5: validacion_minima
P6: =IF(COUNTA($A6:$O6)=0,"",IF(OR($A6="",$B6="",$C6="",$E6=""),"Falta dato obligatorio","Listo"))
P7: =IF(COUNTA($A7:$O7)=0,"",IF(OR($A7="",$B7="",$C7="",$E7=""),"Falta dato obligatorio","Listo"))
P8: =IF(COUNTA($A8:$O8)=0,"",IF(OR($A8="",$B8="",$C8="",$E8=""),"Falta dato obligatorio","Listo"))
P9: =IF(COUNTA($A9:$O9)=0,"",IF(OR($A9="",$B9="",$C9="",$E9=""),"Falta dato obligatorio","Listo"))
P10: =IF(COUNTA($A10:$O10)=0,"",IF(OR($A10="",$B10="",$C10="",$E10=""),"Falta dato obligatorio","Listo"))
P11: =IF(COUNTA($A11:$O11)=0,"",IF(OR($A11="",$B11="",$C11="",$E11=""),"Falta dato obligatorio","Listo"))
P12: =IF(COUNTA($A12:$O12)=0,"",IF(OR($A12="",$B12="",$C12="",$E12=""),"Falta dato obligatorio","Listo"))
P13: =IF(COUNTA($A13:$O13)=0,"",IF(OR($A13="",$B13="",$C13="",$E13=""),"Falta dato obligatorio","Listo"))
P14: =IF(COUNTA($A14:$O14)=0,"",IF(OR($A14="",$B14="",$C14="",$E14=""),"Falta dato obligatorio","Listo"))
P15: =IF(COUNTA($A15:$O15)=0,"",IF(OR($A15="",$B15="",$C15="",$E15=""),"Falta dato obligatorio","Listo"))
P16: =IF(COUNTA($A16:$O16)=0,"",IF(OR($A16="",$B16="",$C16="",$E16=""),"Falta dato obligatorio","Listo"))
P17: =IF(COUNTA($A17:$O17)=0,"",IF(OR($A17="",$B17="",$C17="",$E17=""),"Falta dato obligatorio","Listo"))
... P205: =IF(COUNTA($A205:$O205)=0,"",IF(OR($A205="",$B205="",$C205="",$E205=""),"Falta dato obligatorio","Listo"))

Sheet Productos
A1: Productos
A2: Medicamentos, insumos y equipos que pueden manejarse como inventario o venta.
A3: Campos requeridos: producto_id, nombre_producto, tipo_producto, unidad_medida, estatus
A4: Requerido | B4: Requerido | C4: Requerido | D4: Opcional | E4: Requerido | F4: Opcional | G4: Opcional | H4: Opcional | I4: Opcional | J4: Opcional | K4: Opcional | L4: Opcional | M4: Requerido | N4: Opcional | O4: Calculado
A5: producto_id | B5: nombre_producto | C5: tipo_producto | D5: sku_codigo | E5: unidad_medida | F5: proveedor_preferido_id | G5: costo_unitario | H5: precio_venta | I5: moneda | J5: inventariable | K5: stock_minimo | L5: requiere_receta | M5: estatus | N5: notas | O5: validacion_minima
O6: =IF(COUNTA($A6:$N6)=0,"",IF(OR($A6="",$B6="",$C6="",$E6="",$M6=""),"Falta dato obligatorio","Listo"))
O7: =IF(COUNTA($A7:$N7)=0,"",IF(OR($A7="",$B7="",$C7="",$E7="",$M7=""),"Falta dato obligatorio","Listo"))
O8: =IF(COUNTA($A8:$N8)=0,"",IF(OR($A8="",$B8="",$C8="",$E8="",$M8=""),"Falta dato obligatorio","Listo"))
O9: =IF(COUNTA($A9:$N9)=0,"",IF(OR($A9="",$B9="",$C9="",$E9="",$M9=""),"Falta dato obligatorio","Listo"))
O10: =IF(COUNTA($A10:$N10)=0,"",IF(OR($A10="",$B10="",$C10="",$E10="",$M10=""),"Falta dato obligatorio","Listo"))
O11: =IF(COUNTA($A11:$N11)=0,"",IF(OR($A11="",$B11="",$C11="",$E11="",$M11=""),"Falta dato obligatorio","Listo"))
O12: =IF(COUNTA($A12:$N12)=0,"",IF(OR($A12="",$B12="",$C12="",$E12="",$M12=""),"Falta dato obligatorio","Listo"))
O13: =IF(COUNTA($A13:$N13)=0,"",IF(OR($A13="",$B13="",$C13="",$E13="",$M13=""),"Falta dato obligatorio","Listo"))
O14: =IF(COUNTA($A14:$N14)=0,"",IF(OR($A14="",$B14="",$C14="",$E14="",$M14=""),"Falta dato obligatorio","Listo"))
O15: =IF(COUNTA($A15:$N15)=0,"",IF(OR($A15="",$B15="",$C15="",$E15="",$M15=""),"Falta dato obligatorio","Listo"))
O16: =IF(COUNTA($A16:$N16)=0,"",IF(OR($A16="",$B16="",$C16="",$E16="",$M16=""),"Falta dato obligatorio","Listo"))
O17: =IF(COUNTA($A17:$N17)=0,"",IF(OR($A17="",$B17="",$C17="",$E17="",$M17=""),"Falta dato obligatorio","Listo"))
... O205: =IF(COUNTA($A205:$N205)=0,"",IF(OR($A205="",$B205="",$C205="",$E205="",$M205=""),"Falta dato obligatorio","Listo"))

Sheet Tarifas_Coberturas
A1: Tarifas y coberturas
A2: Relaciona servicios con precios, aseguradoras, autorizaciones y vigencias.
A3: Campos requeridos: tarifa_id, servicio_id, precio_convenio, vigencia_desde, vigencia_hasta, estatus
A4: Requerido | B4: Requerido | C4: Opcional | D4: Opcional | E4: Requerido | F4: Opcional | G4: Opcional | H4: Opcional | I4: Opcional | J4: Opcional | K4: Requerido | L4: Requerido | M4: Requerido | N4: Opcional | O4: Calculado
A5: tarifa_id | B5: servicio_id | C5: seguro_id | D5: proveedor_id | E5: precio_convenio | F5: moneda | G5: cobertura_tipo | H5: cobertura_valor | I5: copago | J5: requiere_autorizacion | K5: vigencia_desde | L5: vigencia_hasta | M5: estatus | N5: notas | O5: validacion_minima
O6: =IF(COUNTA($A6:$N6)=0,"",IF(OR($A6="",$B6="",$E6="",$K6="",$L6="",$M6=""),"Falta dato obligatorio","Listo"))
O7: =IF(COUNTA($A7:$N7)=0,"",IF(OR($A7="",$B7="",$E7="",$K7="",$L7="",$M7=""),"Falta dato obligatorio","Listo"))
O8: =IF(COUNTA($A8:$N8)=0,"",IF(OR($A8="",$B8="",$E8="",$K8="",$L8="",$M8=""),"Falta dato obligatorio","Listo"))
O9: =IF(COUNTA($A9:$N9)=0,"",IF(OR($A9="",$B9="",$E9="",$K9="",$L9="",$M9=""),"Falta dato obligatorio","Listo"))
O10: =IF(COUNTA($A10:$N10)=0,"",IF(OR($A10="",$B10="",$E10="",$K10="",$L10="",$M10=""),"Falta dato obligatorio","Listo"))
O11: =IF(COUNTA($A11:$N11)=0,"",IF(OR($A11="",$B11="",$E11="",$K11="",$L11="",$M11=""),"Falta dato obligatorio","Listo"))
O12: =IF(COUNTA($A12:$N12)=0,"",IF(OR($A12="",$B12="",$E12="",$K12="",$L12="",$M12=""),"Falta dato obligatorio","Listo"))
O13: =IF(COUNTA($A13:$N13)=0,"",IF(OR($A13="",$B13="",$E13="",$K13="",$L13="",$M13=""),"Falta dato obligatorio","Listo"))
O14: =IF(COUNTA($A14:$N14)=0,"",IF(OR($A14="",$B14="",$E14="",$K14="",$L14="",$M14=""),"Falta dato obligatorio","Listo"))
O15: =IF(COUNTA($A15:$N15)=0,"",IF(OR($A15="",$B15="",$E15="",$K15="",$L15="",$M15=""),"Falta dato obligatorio","Listo"))
O16: =IF(COUNTA($A16:$N16)=0,"",IF(OR($A16="",$B16="",$E16="",$K16="",$L16="",$M16=""),"Falta dato obligatorio","Listo"))
O17: =IF(COUNTA($A17:$N17)=0,"",IF(OR($A17="",$B17="",$E17="",$K17="",$L17="",$M17=""),"Falta dato obligatorio","Listo"))
... O205: =IF(COUNTA($A205:$N205)=0,"",IF(OR($A205="",$B205="",$E205="",$K205="",$L205="",$M205=""),"Falta dato obligatorio","Listo"))

Sheet Compras_Proveedor
A1: Compras por proveedor
A2: Relaciona productos con proveedores, costos, cantidades minimas y tiempos de entrega.
A3: Campos requeridos: compra_id, producto_id, proveedor_id, costo_unitario, estatus
A4: Requerido | B4: Requerido | C4: Requerido | D4: Requerido | E4: Opcional | F4: Opcional | G4: Opcional | H4: Opcional | I4: Opcional | J4: Requerido | K4: Opcional | L4: Calculado
A5: compra_id | B5: producto_id | C5: proveedor_id | D5: costo_unitario | E5: moneda | F5: plazo_entrega_dias | G5: cantidad_minima | H5: vigencia_desde | I5: vigencia_hasta | J5: estatus | K5: notas | L5: validacion_minima
L6: =IF(COUNTA($A6:$K6)=0,"",IF(OR($A6="",$B6="",$C6="",$D6="",$J6=""),"Falta dato obligatorio","Listo"))
L7: =IF(COUNTA($A7:$K7)=0,"",IF(OR($A7="",$B7="",$C7="",$D7="",$J7=""),"Falta dato obligatorio","Listo"))
L8: =IF(COUNTA($A8:$K8)=0,"",IF(OR($A8="",$B8="",$C8="",$D8="",$J8=""),"Falta dato obligatorio","Listo"))
L9: =IF(COUNTA($A9:$K9)=0,"",IF(OR($A9="",$B9="",$C9="",$D9="",$J9=""),"Falta dato obligatorio","Listo"))
L10: =IF(COUNTA($A10:$K10)=0,"",IF(OR($A10="",$B10="",$C10="",$D10="",$J10=""),"Falta dato obligatorio","Listo"))
L11: =IF(COUNTA($A11:$K11)=0,"",IF(OR($A11="",$B11="",$C11="",$D11="",$J11=""),"Falta dato obligatorio","Listo"))
L12: =IF(COUNTA($A12:$K12)=0,"",IF(OR($A12="",$B12="",$C12="",$D12="",$J12=""),"Falta dato obligatorio","Listo"))
L13: =IF(COUNTA($A13:$K13)=0,"",IF(OR($A13="",$B13="",$C13="",$D13="",$J13=""),"Falta dato obligatorio","Listo"))
L14: =IF(COUNTA($A14:$K14)=0,"",IF(OR($A14="",$B14="",$C14="",$D14="",$J14=""),"Falta dato obligatorio","Listo"))
L15: =IF(COUNTA($A15:$K15)=0,"",IF(OR($A15="",$B15="",$C15="",$D15="",$J15=""),"Falta dato obligatorio","Listo"))
L16: =IF(COUNTA($A16:$K16)=0,"",IF(OR($A16="",$B16="",$C16="",$D16="",$J16=""),"Falta dato obligatorio","Listo"))
L17: =IF(COUNTA($A17:$K17)=0,"",IF(OR($A17="",$B17="",$C17="",$D17="",$J17=""),"Falta dato obligatorio","Listo"))
... L205: =IF(COUNTA($A205:$K205)=0,"",IF(OR($A205="",$B205="",$C205="",$D205="",$J205=""),"Falta dato obligatorio","Listo"))

Sheet Personal
A1: Personal
A2: Usuarios operativos y personal de atencion que pueden ser asignados a visitas o turnos.
A3: Campos requeridos: personal_id, nombre_completo, funcion, estatus
A4: Requerido | B4: Requerido | C4: Requerido | D4: Opcional | E4: Opcional | F4: Opcional | G4: Opcional | H4: Opcional | I4: Opcional | J4: Requerido | K4: Opcional | L4: Calculado
A5: personal_id | B5: nombre_completo | C5: funcion | D5: registro_profesional | E5: anos_experiencia | F5: correo | G5: telefono | H5: disponibilidad | I5: zona_cobertura | J5: estatus | K5: notas | L5: validacion_minima
L6: =IF(COUNTA($A6:$K6)=0,"",IF(OR($A6="",$B6="",$C6="",$J6=""),"Falta dato obligatorio","Listo"))
L7: =IF(COUNTA($A7:$K7)=0,"",IF(OR($A7="",$B7="",$C7="",$J7=""),"Falta dato obligatorio","Listo"))
L8: =IF(COUNTA($A8:$K8)=0,"",IF(OR($A8="",$B8="",$C8="",$J8=""),"Falta dato obligatorio","Listo"))
L9: =IF(COUNTA($A9:$K9)=0,"",IF(OR($A9="",$B9="",$C9="",$J9=""),"Falta dato obligatorio","Listo"))
L10: =IF(COUNTA($A10:$K10)=0,"",IF(OR($A10="",$B10="",$C10="",$J10=""),"Falta dato obligatorio","Listo"))
L11: =IF(COUNTA($A11:$K11)=0,"",IF(OR($A11="",$B11="",$C11="",$J11=""),"Falta dato obligatorio","Listo"))
L12: =IF(COUNTA($A12:$K12)=0,"",IF(OR($A12="",$B12="",$C12="",$J12=""),"Falta dato obligatorio","Listo"))
L13: =IF(COUNTA($A13:$K13)=0,"",IF(OR($A13="",$B13="",$C13="",$J13=""),"Falta dato obligatorio","Listo"))
L14: =IF(COUNTA($A14:$K14)=0,"",IF(OR($A14="",$B14="",$C14="",$J14=""),"Falta dato obligatorio","Listo"))
L15: =IF(COUNTA($A15:$K15)=0,"",IF(OR($A15="",$B15="",$C15="",$J15=""),"Falta dato obligatorio","Listo"))
L16: =IF(COUNTA($A16:$K16)=0,"",IF(OR($A16="",$B16="",$C16="",$J16=""),"Falta dato obligatorio","Listo"))
L17: =IF(COUNTA($A17:$K17)=0,"",IF(OR($A17="",$B17="",$C17="",$J17=""),"Falta dato obligatorio","Listo"))
... L205: =IF(COUNTA($A205:$K205)=0,"",IF(OR($A205="",$B205="",$C205="",$J205=""),"Falta dato obligatorio","Listo"))
